MANIFEST.in
README.md
requirements.txt
setup.py
foursquare/__init__.py
foursquare/api.py
tornado_foursquare.egg-info/PKG-INFO
tornado_foursquare.egg-info/SOURCES.txt
tornado_foursquare.egg-info/dependency_links.txt
tornado_foursquare.egg-info/requires.txt
tornado_foursquare.egg-info/top_level.txt