Metadata-Version: 1.0
Name: tornado-foursquare
Version: 0.0.2
Summary: A tornado based foursquare api wrapper
Home-page: https://github.com/rafaels88/tornado-foursquare
Author: Rafael Soares
Author-email: rafaelsantos88@gmail.com
License: OSI
Platform: UNKNOWN
